script/AnDOcreator.py
script/__init__.py
script/_version.py
AnDOcreator-0.1.dist-info/METADATA
AnDOcreator-0.1.dist-info/WHEEL
AnDOcreator-0.1.dist-info/entry_points.txt
AnDOcreator-0.1.dist-info/top_level.txt
AnDOcreator-0.1.dist-info/RECORD
