Metadata-Version: 2.1
Name: AnDOcreator
Version: 0.1
Summary: Little tools fo  ANimal Data Organization (ANDO) specifications 
Home-page: UNKNOWN
Author: Jeremy Garcia, Sylvain Takerkart
License: MIT
Platform: UNKNOWN
Requires-Python: >=3.6
Requires-Dist: flake8
Requires-Dist: pytest
